{
 "filename": "zebra_fish0064.jpg",
 "size": 94954,
 "regions": [
  {
   "shape_attributes": {
    "name": "polygon",
    "all_points_x": [
     248,
     261,
     269,
     277,
     292,
     294,
     296,
     290,
     273,
     257,
     245,
     229,
     188,
     151,
     143,
     126,
     114,
     112,
     135,
     199,
     221,
     220,
     232,
     251,
     254
    ],
    "all_points_y": [
     278,
     270,
     257,
     255,
     255,
     267,
     275,
     293,
     314,
     324,
     338,
     360,
     411,
     451,
     473,
     478,
     476,
     459,
     426,
     343,
     310,
     297,
     286,
     274,
     274
    ]
   },
   "region_attributes": {
    "class": "Healthy"
   }
  },
  {
   "shape_attributes": {
    "name": "polygon",
    "all_points_x": [
     369,
     468,
     542,
     564,
     595,
     595,
     585,
     572,
     562,
     546,
     536,
     510,
     448,
     417,
     357,
     342,
     336,
     336,
     339,
     351,
     354
    ],
    "all_points_y": [
     303,
     322,
     337,
     337,
     350,
     367,
     383,
     382,
     390,
     384,
     389,
     381,
     352,
     345,
     327,
     325,
     316,
     307,
     302,
     298,
     298
    ]
   },
   "region_attributes": {
    "class": "Healthy"
   }
  },
  {
   "shape_attributes": {
    "name": "polygon",
    "all_points_x": [
     461,
     497,
     533,
     541,
     547,
     551,
     551,
     545,
     535,
     527,
     517,
     510,
     496,
     434,
     397,
     351,
     306,
     286,
     276,
     275,
     300,
     335,
     358
    ],
    "all_points_y": [
     449,
     438,
     432,
     435,
     444,
     451,
     457,
     468,
     475,
     481,
     485,
     487,
     491,
     497,
     498,
     508,
     515,
     519,
     503,
     491,
     485,
     480,
     475
    ]
   },
   "region_attributes": {
    "class": "Healthy"
   }
  },
  {
   "shape_attributes": {
    "name": "polygon",
    "all_points_x": [
     733,
     721,
     698,
     687,
     685,
     678,
     662,
     649,
     646,
     654,
     671,
     689,
     717,
     729,
     735,
     736,
     724,
     719,
     720,
     729,
     737,
     740,
     740,
     740
    ],
    "all_points_y": [
     418,
     444,
     512,
     531,
     546,
     553,
     554,
     567,
     582,
     623,
     640,
     642,
     634,
     626,
     606,
     580,
     562,
     556,
     533,
     478,
     447,
     428,
     413,
     413
    ]
   },
   "region_attributes": {
    "class": "Balloon"
   }
  },
  {
   "shape_attributes": {
    "name": "polygon",
    "all_points_x": [
     326,
     378,
     405,
     427,
     435,
     439,
     414,
     391,
     358,
     306,
     250,
     240,
     224,
     207,
     196,
     201,
     202,
     206,
     222,
     236,
     265,
     289
    ],
    "all_points_y": [
     595,
     582,
     571,
     566,
     572,
     591,
     595,
     600,
     612,
     630,
     654,
     666,
     671,
     673,
     669,
     656,
     644,
     637,
     616,
     608,
     601,
     599
    ]
   },
   "region_attributes": {
    "class": "Healthy"
   }
  },
  {
   "shape_attributes": {
    "name": "polygon",
    "all_points_x": [
     265,
     280,
     303,
     321,
     342,
     399,
     438,
     463,
     494,
     504,
     502,
     497,
     481,
     456,
     414,
     333,
     305,
     274,
     256,
     240,
     229,
     230,
     236,
     244,
     259
    ],
    "all_points_y": [
     751,
     753,
     753,
     755,
     764,
     772,
     782,
     785,
     788,
     801,
     809,
     817,
     819,
     811,
     811,
     803,
     802,
     808,
     809,
     809,
     799,
     778,
     771,
     757,
     747
    ]
   },
   "region_attributes": {
    "class": "Heart"
   }
  },
  {
   "shape_attributes": {
    "name": "polygon",
    "all_points_x": [
     613,
     638,
     674,
     719,
     757,
     778,
     801,
     812,
     805,
     793,
     769,
     745,
     708,
     660,
     630,
     607,
     585,
     554,
     545,
     545,
     554,
     593
    ],
    "all_points_y": [
     913,
     924,
     941,
     948,
     962,
     963,
     969,
     981,
     991,
     994,
     994,
     987,
     982,
     975,
     964,
     962,
     962,
     954,
     935,
     924,
     913,
     910
    ]
   },
   "region_attributes": {
    "class": "Healthy"
   }
  },
  {
   "shape_attributes": {
    "name": "polygon",
    "all_points_x": [
     248,
     265,
     266,
     254,
     250,
     236,
     209,
     191,
     183,
     160,
     147,
     149,
     163,
     156,
     156,
     173,
     171,
     169,
     182,
     203,
     211,
     213,
     221,
     230,
     240,
     240
    ],
    "all_points_y": [
     935,
     949,
     965,
     977,
     995,
     1010,
     1023,
     1036,
     1061,
     1089,
     1089,
     1070,
     1043,
     1031,
     1007,
     988,
     981,
     963,
     951,
     942,
     942,
     935,
     933,
     931,
     931,
     931
    ]
   },
   "region_attributes": {
    "class": "Balloon"
   }
  },
  {
   "shape_attributes": {
    "name": "polygon",
    "all_points_x": [
     208,
     212,
     220,
     220,
     220,
     221,
     225,
     233,
     238,
     245,
     253,
     256,
     255,
     253,
     251,
     246,
     234,
     227,
     220,
     215,
     208,
     205,
     204,
     204
    ],
    "all_points_y": [
     341,
     334,
     322,
     317,
     309,
     302,
     295,
     285,
     283,
     281,
     287,
     291,
     297,
     304,
     311,
     316,
     323,
     330,
     336,
     342,
     348,
     350,
     348,
     348
    ]
   },
   "region_attributes": {
    "class": "Yolk"
   }
  },
  {
   "shape_attributes": {
    "name": "polygon",
    "all_points_x": [
     460,
     467,
     485,
     501,
     513,
     525,
     534,
     544,
     551,
     554,
     553,
     549,
     545,
     542,
     533,
     525,
     508,
     504,
     496,
     489,
     477,
     470,
     462,
     460
    ],
    "all_points_y": [
     346,
     346,
     348,
     349,
     350,
     350,
     351,
     355,
     359,
     366,
     372,
     377,
     380,
     383,
     384,
     384,
     372,
     366,
     360,
     357,
     353,
     352,
     350,
     349
    ]
   },
   "region_attributes": {
    "class": "Yolk"
   }
  },
  {
   "shape_attributes": {
    "name": "polygon",
    "all_points_x": [
     422,
     430,
     441,
     458,
     470,
     476,
     489,
     491,
     498,
     508,
     509,
     510,
     511,
     507,
     499,
     491,
     479,
     469,
     461,
     449,
     438,
     426,
     418,
     417
    ],
    "all_points_y": [
     485,
     482,
     479,
     472,
     471,
     464,
     461,
     459,
     461,
     466,
     470,
     476,
     482,
     487,
     490,
     491,
     493,
     491,
     488,
     488,
     489,
     491,
     491,
     490
    ]
   },
   "region_attributes": {
    "class": "Yolk"
   }
  },
  {
   "shape_attributes": {
    "name": "polygon",
    "all_points_x": [
     678,
     678,
     679,
     681,
     686,
     691,
     696,
     694,
     694,
     695,
     700,
     706,
     709,
     715,
     715,
     709,
     708,
     709,
     712,
     712,
     708,
     704,
     699,
     697,
     691,
     690,
     688,
     680,
     678
    ],
    "all_points_y": [
     600,
     595,
     586,
     577,
     569,
     563,
     559,
     541,
     536,
     527,
     520,
     516,
     516,
     523,
     546,
     550,
     557,
     564,
     568,
     581,
     589,
     597,
     603,
     608,
     605,
     602,
     601,
     602,
     601
    ]
   },
   "region_attributes": {
    "class": "Yolk"
   }
  },
  {
   "shape_attributes": {
    "name": "polygon",
    "all_points_x": [
     320,
     320,
     313,
     286,
     266,
     259,
     243,
     239,
     229,
     229,
     227,
     231,
     239,
     244,
     255,
     266,
     272,
     280,
     297,
     301,
     306
    ],
    "all_points_y": [
     599,
     603,
     608,
     615,
     625,
     630,
     639,
     639,
     639,
     634,
     618,
     613,
     609,
     608,
     608,
     607,
     603,
     603,
     600,
     600,
     600
    ]
   },
   "region_attributes": {
    "class": "Yolk"
   }
  },
  {
   "shape_attributes": {
    "name": "polygon",
    "all_points_x": [
     385,
     378,
     370,
     356,
     345,
     326,
     317,
     307,
     299,
     291,
     287,
     283,
     277,
     276,
     276,
     276,
     282,
     290,
     302,
     325,
     344,
     357,
     369,
     379,
     387,
     385
    ],
    "all_points_y": [
     779,
     772,
     767,
     767,
     766,
     763,
     760,
     758,
     755,
     755,
     755,
     758,
     765,
     769,
     776,
     780,
     784,
     784,
     785,
     785,
     785,
     784,
     784,
     786,
     785,
     779
    ]
   },
   "region_attributes": {
    "class": "Yolk"
   }
  },
  {
   "shape_attributes": {
    "name": "polygon",
    "all_points_x": [
     208,
     196,
     187,
     186,
     189,
     192,
     200,
     205,
     220,
     221,
     227,
     234,
     234,
     224,
     217
    ],
    "all_points_y": [
     984,
     983,
     983,
     975,
     969,
     957,
     948,
     948,
     952,
     958,
     961,
     970,
     977,
     985,
     985
    ]
   },
   "region_attributes": {
    "class": "Yolk"
   }
  },
  {
   "shape_attributes": {
    "name": "polygon",
    "all_points_x": [
     659,
     643,
     636,
     619,
     614,
     607,
     600,
     594,
     591,
     590,
     592,
     594,
     596,
     601,
     608,
     624,
     636,
     654,
     656
    ],
    "all_points_y": [
     939,
     933,
     929,
     917,
     915,
     914,
     914,
     914,
     921,
     926,
     929,
     935,
     938,
     941,
     942,
     943,
     943,
     942,
     941
    ]
   },
   "region_attributes": {
    "class": "Yolk"
   }
  }
 ],
 "file_attributes": {
  "n_overlaps": "0",
  "overlap_problematic": "False"
 }
}